fastmlapi/__init__.py
fastmlapi/controller.py
fastmlapi/decorators.py
fastmlapi/types.py
fastmlapi-0.1.2.dist-info/licenses/LICENSE
fastmlapi-0.1.2.dist-info/METADATA
fastmlapi-0.1.2.dist-info/WHEEL
fastmlapi-0.1.2.dist-info/top_level.txt
fastmlapi-0.1.2.dist-info/RECORD
