Metadata-Version: 2.4
Name: fastmlapi
Version: 0.1.2
Summary: A FastAPI-based ML worker node library for easy model deployment
Author: Grzegorz Majgier
Maintainer: Grzegorz Majgier
License-Expression: MIT
Project-URL: Homepage, https://github.com/Artificial-Intelligence-in-Medicine-AGH/fast-ML-Api
Project-URL: Documentation, https://github.com/Artificial-Intelligence-in-Medicine-AGH/fast-ML-Api#readme
Project-URL: Repository, https://github.com/Artificial-Intelligence-in-Medicine-AGH/fast-ML-Api
Project-URL: Issues, https://github.com/Artificial-Intelligence-in-Medicine-AGH/fast-ML-Api/issues
Project-URL: Changelog, https://github.com/Artificial-Intelligence-in-Medicine-AGH/fast-ML-Api/blob/main/CHANGELOG.md
Keywords: fastapi,machine-learning,api,ml-serving,model-deployment,ml-ops,inference,model-serving,rest-api,python
Classifier: Development Status :: 3 - Alpha
Classifier: Intended Audience :: Developers
Classifier: Intended Audience :: Science/Research
Classifier: Operating System :: OS Independent
Classifier: Programming Language :: Python :: 3
Classifier: Programming Language :: Python :: 3.9
Classifier: Programming Language :: Python :: 3.10
Classifier: Programming Language :: Python :: 3.11
Classifier: Programming Language :: Python :: 3.12
Classifier: Programming Language :: Python :: 3.13
Classifier: Framework :: FastAPI
Classifier: Framework :: Pydantic :: 2
Classifier: Topic :: Scientific/Engineering :: Artificial Intelligence
Classifier: Topic :: Internet :: WWW/HTTP :: HTTP Servers
Classifier: Topic :: Software Development :: Libraries :: Python Modules
Classifier: Typing :: Typed
Requires-Python: >=3.9
License-File: LICENSE
Requires-Dist: fastapi>=0.100.0
Requires-Dist: uvicorn>=0.23.0
Requires-Dist: pydantic>=2.0.0
Provides-Extra: dev
Requires-Dist: pytest>=7.0.0; extra == "dev"
Requires-Dist: pytest-asyncio>=0.21.0; extra == "dev"
Requires-Dist: httpx>=0.24.0; extra == "dev"
Requires-Dist: numpy>=1.20.0; extra == "dev"
Requires-Dist: ruff>=0.1.0; extra == "dev"
Requires-Dist: mypy>=1.0.0; extra == "dev"
Provides-Extra: docs
Requires-Dist: mkdocs>=1.5.0; extra == "docs"
Requires-Dist: mkdocs-material>=9.0.0; extra == "docs"
Dynamic: license-file
